odoo8_addon_web_tree_date_search-8.0.1.0.0-nspkg.pth
odoo_addons/web_tree_date_search/README.rst
odoo_addons/web_tree_date_search/__init__.py
odoo_addons/web_tree_date_search/__openerp__.py
odoo_addons/web_tree_date_search/demo/demo.xml
odoo_addons/web_tree_date_search/i18n/fr.po
odoo_addons/web_tree_date_search/i18n/nl.po
odoo_addons/web_tree_date_search/static/description/icon.png
odoo_addons/web_tree_date_search/static/src/css/web_tree_date_search.css
odoo_addons/web_tree_date_search/static/src/img/demo.png
odoo_addons/web_tree_date_search/static/src/img/demo1.png
odoo_addons/web_tree_date_search/static/src/js/web_tree_date_search.js
odoo_addons/web_tree_date_search/static/src/xml/web_tree_date_search.xml
odoo_addons/web_tree_date_search/views/assets_backend.xml
odoo8_addon_web_tree_date_search-8.0.1.0.0.dist-info/METADATA
odoo8_addon_web_tree_date_search-8.0.1.0.0.dist-info/WHEEL
odoo8_addon_web_tree_date_search-8.0.1.0.0.dist-info/namespace_packages.txt
odoo8_addon_web_tree_date_search-8.0.1.0.0.dist-info/top_level.txt
odoo8_addon_web_tree_date_search-8.0.1.0.0.dist-info/RECORD
